{
"graph": "1679706190",
"generator": "EvolutionaryBarabasiAlbertGenerator",
"ui.antialias": true,
"ui.quality": true,
"nodes": [
	{
		"id": "0",
		"position": [261.0, 288.0, 0.0],
		"width": 46.0,
		"height": 46.0,
		"degree": 6,
		"intensity": 0.200025,
		"symbol": " ",
		"condition": " "
	},
	{
		"id": "1",
		"position": [266.0, 193.0, 0.0],
		"width": 28.0,
		"height": 28.0,
		"degree": 3,
		"intensity": 0.134964,
		"symbol": " ",
		"condition": " "
	},
	{
		"id": "2",
		"position": [351.0, 339.0, 0.0],
		"width": 34.0,
		"height": 34.0,
		"degree": 4,
		"intensity": 0.218685,
		"symbol": " ",
		"condition": "A"
	},
	{
		"id": "3",
		"position": [272.0, 338.0, 0.0],
		"width": 28.0,
		"height": 28.0,
		"degree": 3,
		"intensity": 0.206906,
		"symbol": " ",
		"condition": "A"
	},
	{
		"id": "4",
		"position": [115.0, 169.0, 0.0],
		"width": 40.0,
		"height": 40.0,
		"degree": 5,
		"intensity": 0.069294,
		"symbol": " ",
		"condition": " "
	},
	{
		"id": "5",
		"position": [287.0, 240.0, 0.0],
		"width": 28.0,
		"height": 28.0,
		"degree": 3,
		"intensity": 0.552074,
		"symbol": " ",
		"condition": "B"
	},
	{
		"id": "6",
		"position": [158.0, 343.0, 0.0],
		"width": 46.0,
		"height": 46.0,
		"degree": 6,
		"intensity": 0.720875,
		"symbol": " ",
		"condition": "C"
	},
	{
		"id": "7",
		"position": [349.0, 400.0, 0.0],
		"width": 28.0,
		"height": 28.0,
		"degree": 3,
		"intensity": 0.425126,
		"symbol": " ",
		"condition": "A"
	},
	{
		"id": "8",
		"position": [235.0, 368.0, 0.0],
		"width": 28.0,
		"height": 28.0,
		"degree": 3,
		"intensity": 0.338671,
		"symbol": " ",
		"condition": "A"
	},
	{
		"id": "9",
		"position": [314.0, 195.0, 0.0],
		"width": 28.0,
		"height": 28.0,
		"degree": 3,
		"intensity": 0.499716,
		"symbol": " ",
		"condition": "B"
	},
	{
		"id": "10",
		"position": [335.0, 73.0, 0.0],
		"width": 28.0,
		"height": 28.0,
		"degree": 3,
		"intensity": 0.426922,
		"symbol": " ",
		"condition": "B"
	},
	{
		"id": "11",
		"position": [258.0, 73.0, 0.0],
		"width": 34.0,
		"height": 34.0,
		"degree": 4,
		"intensity": 0.205044,
		"symbol": " ",
		"condition": " "
	},
	{
		"id": "12",
		"position": [232.0, 240.0, 0.0],
		"width": 22.0,
		"height": 22.0,
		"degree": 2,
		"intensity": 0.259217,
		"symbol": " ",
		"condition": " "
	},
	{
		"id": "13",
		"position": [403.0, 401.0, 0.0],
		"width": 40.0,
		"height": 40.0,
		"degree": 5,
		"intensity": 0.365339,
		"symbol": " ",
		"condition": "A"
	},
	{
		"id": "14",
		"position": [436.0, 461.0, 0.0],
		"width": 28.0,
		"height": 28.0,
		"degree": 3,
		"intensity": 0.437763,
		"symbol": " ",
		"condition": "A"
	},
	{
		"id": "15",
		"position": [450.0, 518.0, 0.0],
		"width": 16.0,
		"height": 16.0,
		"degree": 1,
		"intensity": 0.529207,
		"symbol": "B",
		"condition": "A"
	},
	{
		"id": "16",
		"position": [422.0, 312.0, 0.0],
		"width": 22.0,
		"height": 22.0,
		"degree": 2,
		"intensity": 0.291190,
		"symbol": " ",
		"condition": "A"
	},
	{
		"id": "17",
		"position": [344.0, 455.0, 0.0],
		"width": 22.0,
		"height": 22.0,
		"degree": 2,
		"intensity": 0.472474,
		"symbol": " ",
		"condition": "A"
	},
	{
		"id": "18",
		"position": [458.0, 402.0, 0.0],
		"width": 22.0,
		"height": 22.0,
		"degree": 2,
		"intensity": 0.427216,
		"symbol": " ",
		"condition": "B"
	},
	{
		"id": "19",
		"position": [363.0, 286.0, 0.0],
		"width": 28.0,
		"height": 28.0,
		"degree": 3,
		"intensity": 0.710622,
		"symbol": " ",
		"condition": "C"
	},
	{
		"id": "20",
		"position": [238.0, 217.0, 0.0],
		"width": 16.0,
		"height": 16.0,
		"degree": 1,
		"intensity": 0.705404,
		"symbol": " ",
		"condition": "C"
	},
	{
		"id": "21",
		"position": [157.0, 277.0, 0.0],
		"width": 22.0,
		"height": 22.0,
		"degree": 2,
		"intensity": 0.793133,
		"symbol": " ",
		"condition": "C"
	},
	{
		"id": "22",
		"position": [117.0, 13.0, 0.0],
		"width": 22.0,
		"height": 22.0,
		"degree": 2,
		"intensity": 0.139228,
		"symbol": " ",
		"condition": " "
	},
	{
		"id": "23",
		"position": [79.0, 16.0, 0.0],
		"width": 22.0,
		"height": 22.0,
		"degree": 2,
		"intensity": 0.000000,
		"symbol": "Start",
		"condition": " "
	},
	{
		"id": "24",
		"position": [204.0, 42.0, 0.0],
		"width": 22.0,
		"height": 22.0,
		"degree": 2,
		"intensity": 0.265714,
		"symbol": "A",
		"condition": " "
	},
	{
		"id": "25",
		"position": [23.0, 476.0, 0.0],
		"width": 22.0,
		"height": 22.0,
		"degree": 2,
		"intensity": 0.785071,
		"symbol": " ",
		"condition": "C"
	},
	{
		"id": "26",
		"position": [395.0, 230.0, 0.0],
		"width": 34.0,
		"height": 34.0,
		"degree": 4,
		"intensity": 0.567610,
		"symbol": " ",
		"condition": "B"
	},
	{
		"id": "27",
		"position": [395.0, 179.0, 0.0],
		"width": 28.0,
		"height": 28.0,
		"degree": 3,
		"intensity": 0.616466,
		"symbol": " ",
		"condition": "B"
	},
	{
		"id": "28",
		"position": [181.0, 484.0, 0.0],
		"width": 28.0,
		"height": 28.0,
		"degree": 3,
		"intensity": 0.804126,
		"symbol": " ",
		"condition": "C"
	},
	{
		"id": "29",
		"position": [358.0, 247.0, 0.0],
		"width": 22.0,
		"height": 22.0,
		"degree": 2,
		"intensity": 0.715453,
		"symbol": " ",
		"condition": "C"
	},
	{
		"id": "30",
		"position": [404.0, 132.0, 0.0],
		"width": 22.0,
		"height": 22.0,
		"degree": 2,
		"intensity": 0.675121,
		"symbol": " ",
		"condition": "B"
	},
	{
		"id": "31",
		"position": [468.0, 202.0, 0.0],
		"width": 22.0,
		"height": 22.0,
		"degree": 2,
		"intensity": 0.684441,
		"symbol": " ",
		"condition": "C"
	},
	{
		"id": "32",
		"position": [92.0, 203.0, 0.0],
		"width": 16.0,
		"height": 16.0,
		"degree": 1,
		"intensity": 0.134422,
		"symbol": " ",
		"condition": " "
	},
	{
		"id": "33",
		"position": [112.0, 450.0, 0.0],
		"width": 22.0,
		"height": 22.0,
		"degree": 2,
		"intensity": 0.864201,
		"symbol": " ",
		"condition": "C"
	},
	{
		"id": "34",
		"position": [13.0, 125.0, 0.0],
		"width": 16.0,
		"height": 16.0,
		"degree": 1,
		"intensity": 0.134473,
		"symbol": " ",
		"condition": " "
	},
	{
		"id": "35",
		"position": [396.0, 98.0, 0.0],
		"width": 28.0,
		"height": 28.0,
		"degree": 3,
		"intensity": 0.782980,
		"symbol": " ",
		"condition": "B"
	},
	{
		"id": "36",
		"position": [220.0, 14.0, 0.0],
		"width": 22.0,
		"height": 22.0,
		"degree": 2,
		"intensity": 0.426937,
		"symbol": " ",
		"condition": "B"
	},
	{
		"id": "37",
		"position": [462.0, 79.0, 0.0],
		"width": 16.0,
		"height": 16.0,
		"degree": 1,
		"intensity": 0.872980,
		"symbol": "C",
		"condition": "B"
	},
	{
		"id": "38",
		"position": [9.0, 525.0, 0.0],
		"width": 16.0,
		"height": 16.0,
		"degree": 1,
		"intensity": 1.000000,
		"symbol": "Boss",
		"condition": "C"
	},
	{
		"id": "39",
		"position": [88.0, 356.0, 0.0],
		"width": 28.0,
		"height": 28.0,
		"degree": 3,
		"intensity": 0.880034,
		"symbol": " ",
		"condition": "C"
	},
	{
		"id": "40",
		"position": [83.0, 379.0, 0.0],
		"width": 16.0,
		"height": 16.0,
		"degree": 1,
		"intensity": 0.990000,
		"symbol": " ",
		"condition": "C"
	},
	{
		"id": "41",
		"position": [241.0, 434.0, 0.0],
		"width": 22.0,
		"height": 22.0,
		"degree": 2,
		"intensity": 0.265982,
		"symbol": " ",
		"condition": "A"
	}
],
"edges": [
	{
		"id": "0_1",
		"a": "0",
		"b": "1",
		"symbol": " "
	},
	{
		"id": "0_2",
		"a": "0",
		"b": "2",
		"symbol": "A"
	},
	{
		"id": "0_3",
		"a": "0",
		"b": "3",
		"symbol": "A"
	},
	{
		"id": "0_5",
		"a": "0",
		"b": "5",
		"symbol": "B"
	},
	{
		"id": "0_6",
		"a": "0",
		"b": "6",
		"symbol": "C"
	},
	{
		"id": "0_12",
		"a": "0",
		"b": "12",
		"symbol": " "
	},
	{
		"id": "1_4",
		"a": "1",
		"b": "4",
		"symbol": " "
	},
	{
		"id": "1_11",
		"a": "1",
		"b": "11",
		"symbol": " "
	},
	{
		"id": "2_7",
		"a": "2",
		"b": "7",
		"symbol": " "
	},
	{
		"id": "2_16",
		"a": "2",
		"b": "16",
		"symbol": " "
	},
	{
		"id": "2_19",
		"a": "2",
		"b": "19",
		"symbol": "C"
	},
	{
		"id": "3_8",
		"a": "3",
		"b": "8",
		"symbol": " "
	},
	{
		"id": "3_41",
		"a": "3",
		"b": "41",
		"symbol": " "
	},
	{
		"id": "4_22",
		"a": "4",
		"b": "22",
		"symbol": " "
	},
	{
		"id": "4_23",
		"a": "4",
		"b": "23",
		"symbol": " "
	},
	{
		"id": "4_32",
		"a": "4",
		"b": "32",
		"symbol": " "
	},
	{
		"id": "4_34",
		"a": "4",
		"b": "34",
		"symbol": " "
	},
	{
		"id": "5_9",
		"a": "5",
		"b": "9",
		"symbol": " "
	},
	{
		"id": "5_29",
		"a": "5",
		"b": "29",
		"symbol": "C"
	},
	{
		"id": "6_21",
		"a": "6",
		"b": "21",
		"symbol": " "
	},
	{
		"id": "6_25",
		"a": "6",
		"b": "25",
		"symbol": " "
	},
	{
		"id": "6_28",
		"a": "6",
		"b": "28",
		"symbol": " "
	},
	{
		"id": "6_33",
		"a": "6",
		"b": "33",
		"symbol": " "
	},
	{
		"id": "6_39",
		"a": "6",
		"b": "39",
		"symbol": " "
	},
	{
		"id": "7_13",
		"a": "7",
		"b": "13",
		"symbol": " "
	},
	{
		"id": "7_17",
		"a": "7",
		"b": "17",
		"symbol": " "
	},
	{
		"id": "8_28",
		"a": "8",
		"b": "28",
		"symbol": "C"
	},
	{
		"id": "8_41",
		"a": "8",
		"b": "41",
		"symbol": " "
	},
	{
		"id": "9_10",
		"a": "9",
		"b": "10",
		"symbol": " "
	},
	{
		"id": "9_26",
		"a": "9",
		"b": "26",
		"symbol": " "
	},
	{
		"id": "10_11",
		"a": "10",
		"b": "11",
		"symbol": "B"
	},
	{
		"id": "10_35",
		"a": "10",
		"b": "35",
		"symbol": " "
	},
	{
		"id": "11_24",
		"a": "11",
		"b": "24",
		"symbol": " "
	},
	{
		"id": "11_36",
		"a": "11",
		"b": "36",
		"symbol": "B"
	},
	{
		"id": "12_20",
		"a": "12",
		"b": "20",
		"symbol": "C"
	},
	{
		"id": "13_14",
		"a": "13",
		"b": "14",
		"symbol": " "
	},
	{
		"id": "13_16",
		"a": "13",
		"b": "16",
		"symbol": " "
	},
	{
		"id": "13_17",
		"a": "13",
		"b": "17",
		"symbol": " "
	},
	{
		"id": "13_18",
		"a": "13",
		"b": "18",
		"symbol": "B"
	},
	{
		"id": "14_15",
		"a": "14",
		"b": "15",
		"symbol": " "
	},
	{
		"id": "14_18",
		"a": "14",
		"b": "18",
		"symbol": "B"
	},
	{
		"id": "19_26",
		"a": "19",
		"b": "26",
		"symbol": "C"
	},
	{
		"id": "19_29",
		"a": "19",
		"b": "29",
		"symbol": " "
	},
	{
		"id": "21_39",
		"a": "21",
		"b": "39",
		"symbol": " "
	},
	{
		"id": "22_23",
		"a": "22",
		"b": "23",
		"symbol": " "
	},
	{
		"id": "24_36",
		"a": "24",
		"b": "36",
		"symbol": "B"
	},
	{
		"id": "25_38",
		"a": "25",
		"b": "38",
		"symbol": " "
	},
	{
		"id": "26_27",
		"a": "26",
		"b": "27",
		"symbol": " "
	},
	{
		"id": "26_31",
		"a": "26",
		"b": "31",
		"symbol": "C"
	},
	{
		"id": "27_30",
		"a": "27",
		"b": "30",
		"symbol": " "
	},
	{
		"id": "27_31",
		"a": "27",
		"b": "31",
		"symbol": "C"
	},
	{
		"id": "28_33",
		"a": "28",
		"b": "33",
		"symbol": " "
	},
	{
		"id": "30_35",
		"a": "30",
		"b": "35",
		"symbol": " "
	},
	{
		"id": "35_37",
		"a": "35",
		"b": "37",
		"symbol": " "
	},
	{
		"id": "39_40",
		"a": "39",
		"b": "40",
		"symbol": " "
	}
]
}
